{"name":"About Me","tagline":"","body":"Contact\r\n========\r\n\r\nEmail/XMPP\r\n------------\r\n\r\npapul@riseup.net   \r\nThis is my PGP public key: [papul_riseup.asc](https://raw.github.com/papul/about-me/gh-pages/papul_riseup.asc)\r\n```\r\npub   3072D/60EF0FD7 2013-07-18 [expires: 2018-07-17]\r\n      Key fingerprint = EC3A 17F4 798E 1020 AB1D  C99F E882 3203 60EF 0FD7\r\nuid                  Madhurya Kakati (papul) <papul@riseup.net>\r\nsub   3072g/26336787 2013-07-18 [expires: 2018-07-17]\r\n\r\nOTR fingerprint will be added later.\r\n```\r\n\r\nVOIP\r\n------\r\n\r\nSIP: papul1993@ippi.fr  \r\nSIP numeric: 889435831\r\n\r\n\r\nSkype ID: papul1993\r\n","google":"","note":"Don't delete this file! It's used internally to help with page regeneration."}